irisSeg/DaugmanSegementation.py
irisSeg/__init__.py
irisSeg/command_line.py
irisSeg/utils.py
irisSeg-0.3.dist-info/LICENSE
irisSeg-0.3.dist-info/METADATA
irisSeg-0.3.dist-info/WHEEL
irisSeg-0.3.dist-info/entry_points.txt
irisSeg-0.3.dist-info/top_level.txt
irisSeg-0.3.dist-info/RECORD
