Metadata-Version: 2.1
Name: irisSeg
Version: 0.3
Summary: Daugman implementation to segement iris and pupil
Home-page: http://github.com/mzmmoazam/
Author: mzm
Author-email: mzm.moazam@gmail.com
License: MIT
Keywords: Daugman Daugman's integrodifferential operator iris pupil segementation computer vision
Platform: UNKNOWN
Classifier: Development Status :: 3 - Alpha
Classifier: License :: OSI Approved :: MIT License
Classifier: Programming Language :: Python :: 3
Requires-Dist: cycler (==0.10.0)
Requires-Dist: decorator (==4.4.2)
Requires-Dist: imageio (==2.9.0)
Requires-Dist: irisSeg (==0.2)
Requires-Dist: kiwisolver (==1.3.1)
Requires-Dist: matplotlib (==3.4.2)
Requires-Dist: networkx (==2.5.1)
Requires-Dist: numpy (==1.20.3)
Requires-Dist: opencv-python (==4.5.2.52)
Requires-Dist: Pillow (==8.2.0)
Requires-Dist: pyparsing (==2.4.7)
Requires-Dist: python-dateutil (==2.8.1)
Requires-Dist: PyWavelets (==1.1.1)
Requires-Dist: scikit-image (==0.18.1)
Requires-Dist: scipy (==1.6.3)
Requires-Dist: six (==1.16.0)
Requires-Dist: tifffile (==2021.4.8)
